{
  "schema_version": "comparison_input_v1",
  "system": "synrail",
  "scenario_id": "SCENARIO_HYBRID_003",
  "scenario_class": "medium_risk_ambiguous_closure",
  "task_class": "medium_risk_reversible_artifact_fix",
  "path_id": "hybrid_subset_repair_loop",
  "data_provenance": "curated_local_estimate",
  "closure_result": "ACCEPTED",
  "blocker_to_closure_cycles": 2,
  "false_success_risk": "LOW",
  "proof_completeness": "MEDIUM",
  "recovery_cost": "MEDIUM",
  "coordination_overhead": "MEDIUM",
  "operator_minutes": 28,
  "intervention_count": 3,
  "repair_cycles": 2,
  "invalidation_count": 1,
  "closure_latency_minutes": 31,
  "false_green_exposure": 0,
  "artifact_completeness_percent": 82,
  "notes": "Hybrid still stops on missing scenario proof here, but the baseline already keeps false-green exposure low enough on this reversible ambiguity."
}
